swiss_ai/__init__.py
swiss_ai/autocomplete.py
swiss_ai/cli.py
swiss_ai/cli_enhanced.py
swiss_ai/cli_help.py
swiss_ai/error_handling.py
swiss_ai/progress_feedback.py
swiss_ai/agents/__init__.py
swiss_ai/agents/base.py
swiss_ai/agents/collaborative.py
swiss_ai/agents/implementations.py
swiss_ai/api/__init__.py
swiss_ai/api/client.py
swiss_ai/api/providers.py
swiss_ai/commands/__init__.py
swiss_ai/commands/compliance.py
swiss_ai/commands/context_cmds.py
swiss_ai/commands/intelligence.py
swiss_ai/commands/secure.py
swiss_ai/commands/symphonics.py
swiss_ai/config/__init__.py
swiss_ai/config/manager.py
swiss_ai/context/__init__.py
swiss_ai/context/intelligence.py
swiss_ai/context/validator.py
swiss_ai/mcp/__init__.py
swiss_ai/mcp/manager.py
swiss_ai/models/__init__.py
swiss_ai/models/aliases.py
swiss_ai/models/selector.py
swiss_ai/routing/__init__.py
swiss_ai/routing/router.py
swiss_ai/tui/app.py
swiss_ai/utils/__init__.py
swiss_ai/utils/helpers.py
swiss_ai/utils/security.py
swiss_ai_cli-2.1.3.dist-info/licenses/LICENSE
swiss_ai_cli-2.1.3.dist-info/METADATA
swiss_ai_cli-2.1.3.dist-info/WHEEL
swiss_ai_cli-2.1.3.dist-info/entry_points.txt
swiss_ai_cli-2.1.3.dist-info/top_level.txt
swiss_ai_cli-2.1.3.dist-info/RECORD
